validador_cnpj/__init__.py
validador_cnpj/core.py
validador_cnpj-0.2.3.dist-info/METADATA
validador_cnpj-0.2.3.dist-info/WHEEL
validador_cnpj-0.2.3.dist-info/licenses/LICENSE
validador_cnpj-0.2.3.dist-info/RECORD
