Metadata-Version: 2.4
Name: validador-cnpj
Version: 0.2.3
Summary: UDFs PySpark para limpeza, reparo, normalização e validação de CNPJ (numérico e alfanumérico).
Project-URL: Homepage, https://github.com/data-engineering-bp/validador-cnpj
Project-URL: Issues, https://github.com/data-engineering-bp/validador-cnpj/issues
Author-email: Yuri Arthur Ferreira Santana <yuriarthurf@gmail.com>
License: MIT
License-File: LICENSE
Keywords: brasil,cnpj,data-quality,databricks,pyspark,spark
Classifier: Development Status :: 3 - Alpha
Classifier: Intended Audience :: Developers
Classifier: License :: OSI Approved :: MIT License
Classifier: Programming Language :: Python
Classifier: Programming Language :: Python :: 3
Classifier: Programming Language :: Python :: 3 :: Only
Classifier: Programming Language :: Python :: Implementation :: CPython
Classifier: Topic :: Database :: Database Engines/Servers
Classifier: Topic :: Software Development :: Libraries
Requires-Python: >=3.8
Requires-Dist: pyspark<4.0,>=3.3
